somesy/__init__.py
somesy/cff/__init__.py
somesy/cff/writer.py
somesy/cli/__init__.py
somesy/cli/fill.py
somesy/cli/init.py
somesy/cli/sync.py
somesy/cli/util.py
somesy/codemeta/__init__.py
somesy/codemeta/schema-2.jsonld
somesy/codemeta/utils.py
somesy/codemeta/writer.py
somesy/commands/__init__.py
somesy/commands/init_config.py
somesy/commands/sync.py
somesy/core/__init__.py
somesy/core/core.py
somesy/core/log.py
somesy/core/models.py
somesy/core/types.py
somesy/core/writer.py
somesy/fortran/__init__.py
somesy/fortran/models.py
somesy/fortran/writer.py
somesy/json_wrapper.py
somesy/julia/__init__.py
somesy/julia/models.py
somesy/julia/writer.py
somesy/main.py
somesy/mkdocs/__init__.py
somesy/mkdocs/models.py
somesy/mkdocs/writer.py
somesy/package_json/__init__.py
somesy/package_json/models.py
somesy/package_json/writer.py
somesy/pom_xml/__init__.py
somesy/pom_xml/writer.py
somesy/pom_xml/xmlproxy.py
somesy/pyproject/__init__.py
somesy/pyproject/models.py
somesy/pyproject/writer.py
somesy/rust/__init__.py
somesy/rust/models.py
somesy/rust/writer.py
somesy-0.7.3.dist-info/AUTHORS.md
somesy-0.7.3.dist-info/LICENSE
somesy-0.7.3.dist-info/LICENSES/CC0-1.0.txt
somesy-0.7.3.dist-info/LICENSES/MIT.txt
somesy-0.7.3.dist-info/METADATA
somesy-0.7.3.dist-info/WHEEL
somesy-0.7.3.dist-info/entry_points.txt
somesy-0.7.3.dist-info/RECORD
