Metadata-Version: 2.3
Name: somesy
Version: 0.7.3
Summary: A CLI tool for synchronizing software project metadata.
License: MIT
Keywords: metadata,FAIR
Author: Mustafa Soylu
Author-email: m.soylu@fz-juelich.de
Maintainer: Mustafa Soylu
Maintainer-email: m.soylu@fz-juelich.de
Requires-Python: >=3.8
Classifier: Operating System :: POSIX :: Linux
Classifier: Operating System :: MacOS :: MacOS X
Classifier: Operating System :: Microsoft :: Windows
Classifier: Natural Language :: English
Classifier: Intended Audience :: Developers
Classifier: Intended Audience :: Science/Research
Classifier: Topic :: Software Development :: Libraries :: Application Frameworks
Classifier: License :: OSI Approved :: MIT License
Requires-Dist: cffconvert (>=2.0.0)
Requires-Dist: defusedxml (>=0.7.1)
Requires-Dist: importlib-metadata (>=8.0.0)
Requires-Dist: jinja2 (>=3.1.4)
Requires-Dist: packaging (>=24.1)
Requires-Dist: pydantic[email] (>=2.8.2)
Requires-Dist: pyld (>=2.0.4)
Requires-Dist: ruamel-yaml (>=0.18.6)
Requires-Dist: tomlkit (>=0.13.0)
Requires-Dist: typer[all] (>=0.12.3)
Requires-Dist: wrapt (>=1.16.0)
Project-URL: Documentation, https://materials-data-science-and-informatics.github.io/somesy
Project-URL: Homepage, https://materials-data-science-and-informatics.github.io/somesy
Project-URL: Repository, https://github.com/Materials-Data-Science-and-Informatics/somesy
